Metadata-Version: 1.0
Name: ericsbandnames
Version: 0.3
Summary: Simple client for scraping the contents of ericsbandnames.com, some of which may be offensive, lewd, and/or puerile. However, majority of them are hilarious.
Home-page: https://github.com/PorkShoulderHolder/ericsbandnames
Author: Sam Fox Royston (code), Eric Andre (content)
Author-email: sfoxroyston@gmail.com
License: MIT
Keywords: text,joke,eric andre,nsfw,scraping
Platform: UNKNOWN
